setup.py
SQLAlchemy_SQLSchema.egg-info/PKG-INFO
SQLAlchemy_SQLSchema.egg-info/SOURCES.txt
SQLAlchemy_SQLSchema.egg-info/dependency_links.txt
SQLAlchemy_SQLSchema.egg-info/requires.txt
SQLAlchemy_SQLSchema.egg-info/top_level.txt
sqlalchemy_sqlschema/__init__.py
sqlalchemy_sqlschema/maintain_schema.py
sqlalchemy_sqlschema/sql.py